anchorecli/__init__.py
anchorecli/version.py
anchorecli/cli/__init__.py
anchorecli/cli/evaluate.py
anchorecli/cli/event.py
anchorecli/cli/image.py
anchorecli/cli/policy.py
anchorecli/cli/registry.py
anchorecli/cli/repo.py
anchorecli/cli/subscription.py
anchorecli/cli/system.py
anchorecli/cli/utils.py
anchorecli/clients/__init__.py
anchorecli/clients/apiexternal.py
anchorecli/clients/common.py
anchorecli-0.2.4.dist-info/DESCRIPTION.rst
anchorecli-0.2.4.dist-info/METADATA
anchorecli-0.2.4.dist-info/RECORD
anchorecli-0.2.4.dist-info/WHEEL
anchorecli-0.2.4.dist-info/entry_points.txt
anchorecli-0.2.4.dist-info/metadata.json
anchorecli-0.2.4.dist-info/top_level.txt
