Metadata-Version: 2.0
Name: anchorecli
Version: 0.2.4
Summary: Anchore Service CLI
Home-page: http://www.anchore.com
Author: Anchore Inc.
Author-email: dev@anchore.com
License: Apache License 2.0
Platform: UNKNOWN
Requires-Dist: click
Requires-Dist: prettytable
Requires-Dist: requests
Requires-Dist: urllib3
Requires-Dist: python-dateutil
Requires-Dist: PyYAML
